battlefield1_sdk-1.3.dist-info/DESCRIPTION.rst
battlefield1_sdk-1.3.dist-info/METADATA
battlefield1_sdk-1.3.dist-info/RECORD
battlefield1_sdk-1.3.dist-info/WHEEL
battlefield1_sdk-1.3.dist-info/metadata.json
battlefield1_sdk-1.3.dist-info/top_level.txt
bf1/__init__.py
bf1/api.py
bf1/api_map.py
bf1/battlefield.py
bf1/exceptions.py
bf1/resolvers.py
bf1/config/__init__.py
bf1/config/vehicles.py
bf1/config/weapons.py
