Metadata-Version: 2.0
Name: battlefield1-sdk
Version: 1.3
Summary: Battlefield 1 sdk
Home-page: UNKNOWN
Author: Alessandro De Angelis
Author-email: alessandrodea22@gmail.com
License: MIT
Keywords: Battlefield 1 SDK
Platform: UNKNOWN
Classifier: Development Status :: 2 - Pre-Alpha
Classifier: Intended Audience :: Developers
Classifier: License :: OSI Approved :: MIT License
Classifier: Programming Language :: Python :: 3.5
Classifier: Topic :: Software Development :: Libraries :: Python Modules
Requires-Dist: requests
Requires-Dist: pyOpenSSL
